wiz_mcp/__init__.py
wiz_mcp/server.py
wiz_mcp-0.0.7.dist-info/METADATA
wiz_mcp-0.0.7.dist-info/WHEEL
wiz_mcp-0.0.7.dist-info/entry_points.txt
wiz_mcp-0.0.7.dist-info/licenses/LICENSE
wiz_mcp-0.0.7.dist-info/RECORD
